pandaspgs/__init__.py
pandaspgs/ancestry_category.py
pandaspgs/browser.py
pandaspgs/client.py
pandaspgs/cohort.py
pandaspgs/file_operation.py
pandaspgs/get_ancestry_category.py
pandaspgs/get_cohort.py
pandaspgs/get_performance.py
pandaspgs/get_publication.py
pandaspgs/get_release.py
pandaspgs/get_sample_set.py
pandaspgs/get_score.py
pandaspgs/get_trait.py
pandaspgs/performance.py
pandaspgs/publication.py
pandaspgs/release.py
pandaspgs/sample_set.py
pandaspgs/score.py
pandaspgs/set_operation.py
pandaspgs/trait.py
pandaspgs/trait_category.py
pandaspgs-1.0.0.dist-info/licenses/LICENSE
pandaspgs-1.0.0.dist-info/METADATA
pandaspgs-1.0.0.dist-info/WHEEL
pandaspgs-1.0.0.dist-info/top_level.txt
pandaspgs-1.0.0.dist-info/RECORD
