Metadata-Version: 2.4
Name: pandaspgs
Version: 1.0.0
Summary: A Python package for easy retrieval of Polygenic Score Catalog data
Home-page: https://github.com/tianzelab/pandaspgs
Author: Cao Tianze
Author-email: hnrcao@qq.com
License: MIT
Project-URL: Bug Tracker, https://github.com/tianzelab/pandaspgs/issues
Keywords: pgs,genomics,snp,bioinformatics,pandas
Classifier: Development Status :: 4 - Beta
Classifier: Programming Language :: Python :: 3
Classifier: Programming Language :: Python :: 3.11
Classifier: License :: OSI Approved :: MIT License
Classifier: Operating System :: OS Independent
Requires-Python: >=3.11
License-File: LICENSE
Requires-Dist: pandas>=2.1.4
Requires-Dist: requests>=2.31.0
Requires-Dist: progressbar2>=4.4.2
Requires-Dist: cachetools>=5.3.3
Dynamic: author
Dynamic: author-email
Dynamic: classifier
Dynamic: description
Dynamic: description-content-type
Dynamic: home-page
Dynamic: keywords
Dynamic: license
Dynamic: license-file
Dynamic: project-url
Dynamic: requires-dist
Dynamic: requires-python
Dynamic: summary
